Metadata-Version: 2.1
Name: rl
Version: 3.2
Summary: Alternative Python bindings for GNU Readline
Home-page: https://github.com/stefanholek/rl
Author: Stefan H. Holek
Author-email: stefan@epy.co.at
License: GPLv3
Project-URL: Documentation, https://rl.readthedocs.io/en/stable/
Keywords: gnu,readline,bindings,gnureadline,completion,tab completion
Classifier: Development Status :: 5 - Production/Stable
Classifier: Intended Audience :: Developers
Classifier: License :: OSI Approved :: GNU General Public License v3 (GPLv3)
Classifier: Operating System :: MacOS :: MacOS X
Classifier: Operating System :: POSIX
Classifier: Programming Language :: C
Classifier: Programming Language :: Python
Classifier: Programming Language :: Python :: 2
Classifier: Programming Language :: Python :: 3
Classifier: Programming Language :: Python :: Implementation :: CPython
Requires-Python: >=2.7,!=3.0.*,!=3.1.*,!=3.2.*,!=3.3.*
License-File: LICENSE
Provides-Extra: docs
Requires-Dist: sphinx==5.3.0; extra == "docs"
Requires-Dist: sphinx-rtd-theme==1.0.0; extra == "docs"
